coreason_auditor/__init__.py
coreason_auditor/aibom_generator.py
coreason_auditor/config.py
coreason_auditor/csv_generator.py
coreason_auditor/exceptions.py
coreason_auditor/interfaces.py
coreason_auditor/job_manager.py
coreason_auditor/main.py
coreason_auditor/mocks.py
coreason_auditor/models.py
coreason_auditor/orchestrator.py
coreason_auditor/pdf_generator.py
coreason_auditor/server.py
coreason_auditor/session_replayer.py
coreason_auditor/signer.py
coreason_auditor/traceability_engine.py
coreason_auditor/utils/__init__.py
coreason_auditor/utils/logger.py
coreason_auditor/utils/seeder.py
coreason_auditor-0.3.0.dist-info/METADATA
coreason_auditor-0.3.0.dist-info/WHEEL
coreason_auditor-0.3.0.dist-info/licenses/LICENSE
coreason_auditor-0.3.0.dist-info/licenses/LICENSE_HEADER.txt
coreason_auditor-0.3.0.dist-info/licenses/NOTICE
coreason_auditor-0.3.0.dist-info/RECORD
