Metadata-Version: 2.4
Name: coreason_auditor
Version: 0.3.0
Summary: coreason-auditor
License: # The Prosperity Public License 3.0.0
License-File: LICENSE
License-File: LICENSE_HEADER.txt
License-File: NOTICE
Author: Gowtham A Rao
Author-email: gowtham.rao@coreason.ai
Requires-Python: >=3.11
Classifier: License :: Other/Proprietary License
Classifier: Programming Language :: Python :: 3.12
Classifier: Operating System :: OS Independent
Requires-Dist: aiofiles (>=23.2.1,<24.0.0)
Requires-Dist: anyio (>=4.12.1,<5.0.0)
Requires-Dist: coreason-identity (>=0.1.0,<0.2.0)
Requires-Dist: cryptography (>=46.0.3,<47.0.0)
Requires-Dist: cyclonedx-python-lib (>=11.6.0,<12.0.0)
Requires-Dist: fastapi
Requires-Dist: httpx (>=0.28.1,<0.29.0)
Requires-Dist: loguru (>=0.7.2,<0.8.0)
Requires-Dist: pydantic (>=2.12.5,<3.0.0)
Requires-Dist: pydantic-settings (>=2.12.0,<3.0.0)
Requires-Dist: python-multipart
Requires-Dist: pyyaml (>=6.0.3,<7.0.0)
Requires-Dist: reportlab (>=4.4.9,<5.0.0)
Requires-Dist: uvicorn
Project-URL: Documentation, https://github.com/CoReason-AI/coreason_auditor
Project-URL: Homepage, https://github.com/CoReason-AI/coreason_auditor
Project-URL: Repository, https://github.com/CoReason-AI/coreason_auditor
